{
	"configurations" : 
	[
		{
			"directories" : 
			[
				{
					"build" : ".",
					"jsonFile" : "directory-.-Debug-d0094a50bb2071803777.json",
					"minimumCMakeVersion" : 
					{
						"string" : "3.5"
					},
					"projectIndex" : 0,
					"source" : ".",
					"targetIndexes" : 
					[
						0
					]
				}
			],
			"name" : "Debug",
			"projects" : 
			[
				{
					"directoryIndexes" : 
					[
						0
					],
					"name" : "2D_Racing",
					"targetIndexes" : 
					[
						0
					]
				}
			],
			"targets" : 
			[
				{
					"directoryIndex" : 0,
					"id" : "2D_Racing::@6890427a1f51a3e7e1df",
					"jsonFile" : "target-2D_Racing-Debug-71fbf5b150497b42dccd.json",
					"name" : "2D_Racing",
					"projectIndex" : 0
				}
			]
		}
	],
	"kind" : "codemodel",
	"paths" : 
	{
		"build" : "D:/frank_work/2DRacing/build",
		"source" : "D:/frank_work/2DRacing"
	},
	"version" : 
	{
		"major" : 2,
		"minor" : 6
	}
}
